{
  "info": {
    "_postman_id": "0e6f47c0-6cd9-4979-a0a4-556b0ff87e6a",
    "name": "flumeai-assignment",
    "schema": "https://schema.getpostman.com/json/collection/v2.1.0/collection.json",
    "_exporter_id": "24144534"
  },
  "item": [
    {
      "name": "Authentication",
      "item": [
        {
          "name": "logout",
          "request": {
            "method": "GET",
            "header": [],
            "url": {
              "raw": "{{server}}/auth/logout",
              "host": [
                "{{server}}"
              ],
              "path": [
                "auth",
                "logout"
              ]
            }
          },
          "response": []
        },
        {
          "name": "signup",
          "request": {
            "method": "POST",
            "header": [],
            "body": {
              "mode": "raw",
              "raw": "{\n    \"username\": \"test\",\n    \"password\": \"test@123\",\n    \"confirm_password\": \"test@123\"\n}",
              "options": {
                "raw": {
                  "language": "json"
                }
              }
            },
            "url": {
              "raw": "{{server}}/auth/signup",
              "host": [
                "{{server}}"
              ],
              "path": [
                "auth",
                "signup"
              ]
            }
          },
          "response": []
        },
        {
          "name": "login",
          "request": {
            "method": "POST",
            "header": [],
            "body": {
              "mode": "raw",
              "raw": "{\n    \"username\": \"test\",\n    \"password\": \"test@123\"\n}",
              "options": {
                "raw": {
                  "language": "json"
                }
              }
            },
            "url": {
              "raw": "{{server}}/auth/login",
              "host": [
                "{{server}}"
              ],
              "path": [
                "auth",
                "login"
              ]
            }
          },
          "response": []
        }
      ]
    }
  ]
}